<msbt attribsize="0">
	<message label="DiveFish_02620"><tag a="50" b="0" arg="0x400 0xcd03" />seaweed</message>
	<message label="DiveFish_02830"><tag a="50" b="0" arg="0x400 0xcd03" />sea grapes</message>
	<message label="DiveFish_02831"><tag a="50" b="0" arg="0x100 0xcd03" />sea urchin</message>
	<message label="DiveFish_02832"><tag a="50" b="0" arg="0x200 0xcd03" />acorn barnacle</message>
	<message label="DiveFish_02833"><tag a="50" b="0" arg="0x200 0xcd03" />oyster</message>
	<message label="DiveFish_02834"><tag a="50" b="0" arg="0x100 0xcd03" />turban shell</message>
	<message label="DiveFish_02835"><tag a="50" b="0" arg="0x200 0xcd03" />abalone</message>
	<message label="DiveFish_02838"><tag a="50" b="0" arg="0x100 0xcd03" />pearl oyster</message>
	<message label="DiveFish_02839"><tag a="50" b="0" arg="0x100 0xcd03" />scallop</message>
	<message label="DiveFish_02840"><tag a="50" b="0" arg="0x100 0xcd03" />sea anemone</message>
	<message label="DiveFish_02841"><tag a="50" b="0" arg="0x100 0xcd03" />sea star</message>
	<message label="DiveFish_02842"><tag a="50" b="0" arg="0x100 0xcd03" />sea cucumber</message>
	<message label="DiveFish_02843"><tag a="50" b="0" arg="0x100 0xcd03" />sea slug</message>
	<message label="DiveFish_02844"><tag a="50" b="0" arg="0x100 0xcd03" />flatworm</message>
	<message label="DiveFish_02845"><tag a="50" b="0" arg="0x100 0xcd03" />mantis shrimp</message>
	<message label="DiveFish_02846"><tag a="50" b="0" arg="0x100 0xcd03" />sweet shrimp</message>
	<message label="DiveFish_02847"><tag a="50" b="0" arg="0x100 0xcd03" />tiger prawn</message>
	<message label="DiveFish_02848"><tag a="50" b="0" arg="0x100 0xcd03" />spiny lobster</message>
	<message label="DiveFish_02849"><tag a="50" b="0" arg="0x100 0xcd03" />lobster</message>
	<message label="DiveFish_02850"><tag a="50" b="0" arg="0x100 0xcd03" />snow crab</message>
	<message label="DiveFish_02852"><tag a="50" b="0" arg="0x100 0xcd03" />red king crab</message>
	<message label="DiveFish_02853"><tag a="50" b="0" arg="0x100 0xcd03" />spider crab</message>
	<message label="DiveFish_02854"><tag a="50" b="0" arg="0x200 0xcd03" />octopus</message>
	<message label="DiveFish_02855"><tag a="50" b="0" arg="0x100 0xcd03" />spotted garden eel</message>
	<message label="DiveFish_02856"><tag a="50" b="0" arg="0x100 0xcd03" />chambered nautilus</message>
	<message label="DiveFish_02857"><tag a="50" b="0" arg="0x100 0xcd03" />horseshoe crab</message>
	<message label="DiveFish_02858"><tag a="50" b="0" arg="0x100 0xcd03" />giant isopod</message>
	<message label="DiveFish_06920"><tag a="50" b="0" arg="0x100 0xcd03" />firefly squid</message>
	<message label="DiveFish_07191"><tag a="50" b="0" arg="0x100 0xcd03" />gazami crab</message>
	<message label="DiveFish_07203"><tag a="50" b="0" arg="0x100 0xcd03" />vampire squid</message>
	<message label="DiveFish_07214"><tag a="50" b="0" arg="0x100 0xcd03" />gigas giant clam</message>
	<message label="DiveFish_07228"><tag a="50" b="0" arg="0x100 0xcd03" />sea pineapple</message>
	<message label="DiveFish_07245"><tag a="50" b="0" arg="0x100 0xcd03" />moon jellyfish</message>
	<message label="DiveFish_07252"><tag a="50" b="0" arg="0x200 0xcd03" />umbrella octopus</message>
	<message label="DiveFish_07267"><tag a="50" b="0" arg="0x100 0xcd03" />slate pencil urchin</message>
	<message label="DiveFish_07278"><tag a="50" b="0" arg="0x100 0xcd03" />whelk</message>
	<message label="DiveFish_07303"><tag a="50" b="0" arg="0x100 0xcd03" />sea pig</message>
	<message label="DiveFish_07308"><tag a="50" b="0" arg="0x100 0xcd03" />Dungeness crab</message>
	<message label="DiveFish_07318"><tag a="50" b="0" arg="0x100 0xcd03" />Venus' flower basket</message>
	<message label="DiveFish_07411"><tag a="50" b="0" arg="0x100 0xcd03" />mussel</message>
</msbt>