<msbt attribsize="8">
	<message label="001" attrib="00 00 00 01 00 00 00 00"><anim id="OhGeez" target="actor" targetSpec="" />You hear about <tag a="115" b="1" arg="0xcd00" />
bein' too sick to climb outta bed?<pageBreak /><anim id="Thinking" target="actor" targetSpec="" /><gender3 m="He" f="She" /> oughta be fine with a little
<colour id="1" />medicine<colour id="65535" /> and some rest, but I dunno.<delay frames="60" />
<anim id="Confused" target="actor" targetSpec="" />I can't shake this worry, y'know?</message>
	<message label="002" attrib="00 00 00 01 00 00 00 00"><anim id="OhGeez" target="actor" targetSpec="" />Yikes<tag a="110" b="0" /><delay20 /> I hear <tag a="115" b="1" arg="0xcd00" />
ain't feelin' so hot.<pageBreak /><anim id="Nodding" target="actor" targetSpec="" />Y'know what always cheers me up
when I'm sick? <delay frames="40" /><anim id="Smiling" target="actor" targetSpec="" />Seein' a friendly face.<delay20 />
Whaddaya say, <tag a="110" b="5" />?</message>
	<message label="003" attrib="00 00 00 01 00 00 00 00"><anim id="OhGeez" target="actor" targetSpec="" />You been to see <tag a="115" b="1" arg="0xcd00" />
lately?<delay20 /> I hear <gender3 m="he" f="she" />'s had better days.<pageBreak /><anim id="Negative" target="actor" targetSpec="" />Some <colour id="1" />medicine<colour id="65535" /> and bed rest oughta
fix <gender3 m="him" f="her" /> right up<tag a="110" b="0" /><anim id="Thinking" target="actor" targetSpec="" />but I know firsthand
it's rough bein' sick alone.</message>
</msbt>