<msbt attribsize="8">
	<message label="100" attrib="00 00 00 00 00 00 00 00"><anim id="Hesitate" target="actor" targetSpec="" />I'm done. <delay20 />Life goal achieved. <delay20 />That
<tag a="115" b="1" arg="0xcd00" /> had the nerve to
tell me I look rad in this outfit.<pageBreak /><anim id="Sighing" target="actor" targetSpec="" />I mean, yeah, <delay20 />NOW it sounds like a
normal thing to say. <delay20 />Just<tag a="110" b="0" /><delay20 /><anim id="Blushing" target="actor" targetSpec="" />no one
ever says stuff like that to me! <delay frames="40" />Aaah!<anim id="EmotEnd" target="actor" targetSpec="" /></message>
	<message label="101" attrib="00 00 00 00 00 00 00 00"><anim id="Explain" target="actor" targetSpec="" />My mind is blown. <delay20 />There's this band
I've been into since forever<tag a="110" b="0" /><delay20 />and
<tag a="115" b="1" arg="0xcd00" /> likes 'em too!<pageBreak /><anim id="Smiling" target="actor" targetSpec="" />Just shows you never can tell, huh?<delay frames="40" />
<anim id="HappyDance" target="actor" targetSpec="" />I'm so psyched to freak out over the
new album with someone else!<anim id="EmotEnd" target="actor" targetSpec="" /></message>
	<message label="102" attrib="00 00 00 00 00 00 00 00">I was talkin' with <tag a="115" b="1" arg="0xcd00" />
and <gender3 m="he" f="she" /> said <gender3 m="he" f="she" /> could talk to
me till the sun comes up!<pageBreak /><anim id="Blushing" target="actor" targetSpec="" /><gender3 m="He" f="She" />'s sayin' <gender3 m="he" f="she" /> likes chatting with
me SO MUCH that <gender3 m="he" f="she" /> loses track of
time, <tag a="110" b="5" />.<delay frames="40" /> Awww!<anim id="EmotEnd" target="actor" targetSpec="" /></message>
	<message label="200" attrib="00 00 00 00 00 00 00 00">Y'know<tag a="110" b="0" /><delay20 /><anim id="Blushing" target="actor" targetSpec="" />seems like you and me've
gotten into realer stuff lately
without even noticing.<pageBreak /><anim id="FaintSmile" target="actor" targetSpec="" />Usually I'd be embarrassed about it,
but nah. <delay20 />It's chill. <delay20 /><anim id="HappyFlower" target="actor" targetSpec="" />I'd talk about
anything with you, <tag a="110" b="5" />.<anim id="EmotEnd" target="actor" targetSpec="" /></message>
	<message label="201" attrib="00 00 00 00 00 00 00 00"><anim id="ShyBoy" target="actor" targetSpec="" />Guess it's true that some stuff you
can't get out without sittin' down
and hashing things out like this.<pageBreak /><anim id="FaintSmile" target="actor" targetSpec="" />Hah! <delay20 />That's the best thing about you,
<tag a="110" b="3" />. <delay20 /><anim id="HappyFlower" target="actor" targetSpec="" />We really GET
each other, <tag a="110" b="5" />.<anim id="EmotEnd" target="actor" targetSpec="" /></message>
	<message label="202" attrib="00 00 00 00 00 00 00 00"><anim id="Explain" target="actor" targetSpec="" />It's so good to be able to let my hair
down. <delay frames="40" /><anim id="Nodding" target="actor" targetSpec="" />I can vent about whatever to
you. <delay20 />That's REAL friendship!<pageBreak /><anim id="FaintSmile" target="actor" targetSpec="" />What I'm gettin' at here is, <delay frames="40" /><anim id="HappyDance" target="actor" targetSpec="" />we should
hang out more, <tag a="110" b="3" />.<anim id="EmotEnd" target="actor" targetSpec="" /></message>
</msbt>