<msbt attribsize="8">
	<message label="001" attrib="00 00 00 00 00 00 00 00"><anim id="WrySmile" target="actor" targetSpec="" />You know that tiny little stone has
secret messages written in three
languages on it, <tag a="110" b="5" />?<pageBreak /><anim id="Grin" target="actor" targetSpec="" />And each one of 'em is someone's
shoppin' list. <delay20 /><anim id="Laughing" target="actor" targetSpec="" />Gahaha!</message>
	<message label="002" attrib="00 00 00 00 00 00 00 00"><anim id="Thinking" target="actor" targetSpec="" />Hmm.<10_4 /> <anim id="Explain" target="actor" targetSpec="" />I like the wings, but I think I'd
miss my arms too much.<delay20 /> No trade!<delay frames="40" />
<anim id="Negative" target="actor" targetSpec="" />And I'm definitely keepin' the head!</message>
	<message label="003" attrib="00 00 00 00 00 00 00 00"><anim id="Worried" target="actor" targetSpec="" />This poor guy's gotta stand there
without any shorts for all of eternity.<delay frames="40" />
<anim id="Shocked" target="actor" targetSpec="" />Wait, where are MY shorts?!</message>
	<message label="004" attrib="00 00 00 00 00 00 00 00"><anim id="Thinking" target="actor" targetSpec="" />Even I know this one. <delay20 />That little
smirk she's doin' sure has a lotta
folks stumped, <tag a="110" b="5" /><tag a="110" b="0" /></message>
	<message label="005" attrib="00 00 00 00 00 00 00 00"><anim id="Eh" target="actor" targetSpec="" />Yeah, that's a pretty big shell.<10_4 />
<anim id="OhGeez" target="actor" targetSpec="" />But I've seen bigger.</message>
	<message label="006" attrib="00 00 00 00 00 00 00 00"><anim id="AbsentMindedness" target="actor" targetSpec="" />Ah, this reminds me of me and
my pals back in the old days when
we wore those foofy collars.
<anim id="Laughing" target="actor" targetSpec="" />Gahaha!<delay20 /> I'm just foolin'. <delay20 /><anim id="Shocked" target="actor" targetSpec="" />How old
do you think I am, anyhow?</message>
	<message label="007" attrib="00 00 00 00 00 00 00 00"><anim id="OhGeez" target="actor" targetSpec="" />Aww, they probably made those kids
sit still for WAAAY too long while
they were paintin' that one.
<anim id="Grin" target="actor" targetSpec="" />If they're like me, they were probably
out doin' a little <tag a="135" b="6" arg="0xcd00" /> the
second this little art session ended!</message>
	<message label="008" attrib="00 00 00 00 00 00 00 00"><anim id="BigSmile" target="actor" targetSpec="" />Talk about a paintin' that gets you
fired up! <delay20 />I'm ready to run through a
brick wall after lookin' at this one!</message>
	<message label="009" attrib="00 00 00 00 00 00 00 00"><anim id="Worried" target="actor" targetSpec="" />Aw, geez<tag a="110" b="0" /> This one's a masterpiece,
but I'm not gonna hang it over the
mantle, if you catch my drift<tag a="110" b="0" /></message>
	<message label="010" attrib="00 00 00 00 00 00 00 00"><anim id="Silent" target="actor" targetSpec="" />I tell ya, when I take the ol' boat
out, I'm stayin' AWAY from that
place. <delay frames="40" /><anim id="ColdChill" target="actor" targetSpec="" />Gives me the creeps!</message>
	<message label="011" attrib="00 00 00 00 00 00 00 00"><anim id="QuestionMark" target="actor" targetSpec="" />You ever notice that this one's just
a buncha tiny dots?<delay frames="40" /> <anim id="Frantic" target="actor" targetSpec="" />Not sayin' it's
bad, just<tag a="110" b="0" /> It's tiny dots!</message>
	<message label="012" attrib="00 00 00 00 00 00 00 00"><anim id="Nodding" target="actor" targetSpec="" />Ah, yeah, I've seen this one before.<delay20 />
It's real good.<delay20 /> <anim id="Grin" target="actor" targetSpec="" />I couldn't fingerpaint
anything HALF as good.</message>
	<message label="013" attrib="00 00 00 00 00 00 00 00"><anim id="BigSmile" target="actor" targetSpec="" />Surf's up, kiddo! <delay20 />Gahaha! <delay frames="40" /><anim id="SmugFace" target="actor" targetSpec="" />I coulda
hung at least 10 on that wave when
I was a youngster, <tag a="110" b="5" />.</message>
	<message label="014" attrib="00 00 00 00 00 00 00 00"><anim id="OhGeez" target="actor" targetSpec="" />These old action figures are pretty
neat, but I'm pretty sure I'd break
100 percent of 'em on day one.</message>
	<message label="015" attrib="00 00 00 00 00 00 00 00"><anim id="AbsentMindedness" target="actor" targetSpec="" />Whoa<tag a="110" b="0" />that thing feels like it's
important. <delay20 />Like it MEANS somethin',
kiddo.<delay20 /> <anim id="Frantic" target="actor" targetSpec="" />But what? <delay20 />WHAT?!</message>
	<message label="016" attrib="00 00 00 00 00 00 00 00"><anim id="Serious" target="actor" targetSpec="" />I know exactly how this guy feels.<delay20 />
Just sittin' there thinkin' about one
of life's ineffable mysteries<tag a="110" b="0" /><pageBreak /><anim id="Angry" target="actor" targetSpec="" />Like where did I leave my stinkin'
house keys?!</message>
	<message label="101" attrib="00 00 00 00 00 00 00 00"><anim id="Aha" target="actor" targetSpec="" />Hold the <tag a="135" b="5" arg="0xcd00" /><tag a="110" b="0" /><delay20 /> You're the
one who donated this thing, aren't
ya?<10_4 /> <anim id="Cheering" target="actor" targetSpec="" />That's mighty generous, kiddo!</message>
</msbt>