<msbt attribsize="8">
	<message label="001" attrib="00 00 00 00 00 00 00 00"><anim id="Thinking" target="actor" targetSpec="" />Guess they got the "crab"<delay8 /> part
right<tag a="110" b="0" />but that thing doesn't
look like a horseshoe at all!</message>
	<message label="002" attrib="00 00 00 00 00 00 00 00"><anim id="Negative" target="actor" targetSpec="" />Now if that ain't the least-appetizin'
pineapple I've ever seen<tag a="110" b="0" /></message>
	<message label="003" attrib="00 00 00 00 00 00 00 00"><anim id="Negative" target="actor" targetSpec="" />Turns out this here <tag a="50" b="0" arg="0x100 0xcd03" />lobster is some
kind of Rock Paper Scissors genius.<pageBreak /><anim id="OhGeez" target="actor" targetSpec="" />It ain't picked nothin' but scissors
in over <tag a="90" b="1" arg="0x100" /> rounds<tag a="110" b="0" /><delay20 />and I <delay20 /><anim id="Fuming" target="actor" targetSpec="" />still<delay8 /> keep
losin', <tag a="110" b="5" />!<pageBreak /><anim id="Sighing" target="actor" targetSpec="" />Maybe I've lost my touch<tag a="110" b="0" /></message>
	<message label="004" attrib="00 00 00 00 00 00 00 00"><anim id="Pardon" target="actor" targetSpec="" />Wow! <delay8 />Just look at the size of that
<tag a="50" b="0" arg="0x100 0xcd03" />gigas giant clam, <tag a="110" b="5" />!<pageBreak /><anim id="Nodding" target="actor" targetSpec="" />I'm having a hard time staying clam
here.<10_4 /> <anim id="Blushing" target="actor" targetSpec="" />Uh<tag a="110" b="0" />calm. <delay20 />I meant to say calm.</message>
	<message label="005" attrib="00 00 00 00 00 00 00 00"><anim id="Serious" target="actor" targetSpec="" />An <tag a="50" b="0" arg="0x200 0xcd03" />umbrella octopus, huh?<delay frames="40" /> <anim id="ShyBoy" target="actor" targetSpec="" />Gotta be
a serious umbrella to stay dry under
THAT<delay8 /> much water, <tag a="110" b="5" /><tag a="110" b="0" /></message>
	<message label="006" attrib="00 00 00 00 00 00 00 00"><anim id="HappyDance" target="actor" targetSpec="" />Well now, <delay8 />it's quite an honor to be
in the presence of His Highness the
<tag a="50" b="0" arg="0x100 0xcd03" />red king crab, <tag a="110" b="5" />.<pageBreak /><anim id="Explain" target="actor" targetSpec="" />It ain't often we get royalty
visitin' <tag a="110" b="8" />.</message>
	<message label="007" attrib="00 00 00 00 00 00 00 00"><anim id="Negative" target="actor" targetSpec="" />I just don't know what to make of
this here <tag a="50" b="0" arg="0x100 0xcd03" />moon jellyfish. <delay20 />The way it's
all flimsy and see-through<tag a="110" b="0" /><pageBreak /><anim id="Shaking" target="actor" targetSpec="" />Gives me the willies, <tag a="110" b="5" />.</message>
	<message label="008" attrib="00 00 00 00 00 00 00 00"><anim id="QuestionMark" target="actor" targetSpec="" />What if a <tag a="50" b="0" arg="0x100 0xcd03" />chambered nautilus wants
itself a bigger shell?<pageBreak /><anim id="Thinking" target="actor" targetSpec="" />Think there's like a<tag a="110" b="0" />Tom Nautilus or
somethin' out there he can wrangle
a loan from, <tag a="110" b="5" />?</message>
	<message label="009" attrib="00 00 00 00 00 00 00 00"><anim id="ShyBoy" target="actor" targetSpec="" />Well, as long as they ain't spinnin'
webs for me to walk face first into,<delay8 />
then <tag a="50" b="0" arg="0x100 0xcd03" />spider crabs are alright by me.</message>
	<message label="010" attrib="00 00 00 00 00 00 00 00"><anim id="Worried" target="actor" targetSpec="" />Considerin' the sea creatures that
get called "giant," I guess I figured
a <tag a="50" b="0" arg="0x100 0xcd03" />giant isopod'd be<tag a="110" b="0" /><delay20 /><anim id="OhGeez" target="actor" targetSpec="" />giant-er.</message>
	<message label="101" attrib="00 00 00 00 00 00 00 00"><anim id="QuestionMark" target="actor" targetSpec="" />Did I hear right? <delay20 />You donated this
fine specimen?<delay20 /> <anim id="BigSmile" target="actor" targetSpec="" />That's some fine
divin' skill you got, <tag a="110" b="5" />.</message>
</msbt>