<msbt attribsize="8">
	<message label="001" attrib="00 00 0c 01 00 00 00 00"><anim id="FaintSmile" target="actor" targetSpec="" />Glad you reached out to me again.<10_4 />
<anim id="QuestionMark" target="actor" targetSpec="" />How can I help you,<delay20 /> <tag a="110" b="5" />?<setNpcTalkChoices chatOption="0" cancelOption="0" /></message>
	<message label="002" attrib="00 00 0c 01 00 00 00 00"><anim id="Smiling" target="actor" targetSpec="" />What's on your mind,<delay20 /> <tag a="110" b="5" />?<setNpcTalkChoices chatOption="0" cancelOption="0" /></message>
	<message label="003" attrib="00 00 0c 01 00 00 00 00"><anim id="Laughing" target="actor" targetSpec="" />We just keep running into each
other,<delay20 /> <tag a="110" b="1" />!<10_4 />
<anim id="FaintSmile" target="actor" targetSpec="" />What's up,<delay20 /> <tag a="110" b="5" />?<setNpcTalkChoices chatOption="0" cancelOption="0" /></message>
</msbt>