<msbt attribsize="8">
	<message label="001" attrib="00 00 00 00 00 00 00 00"><tag a="60" b="20" /></message>
	<message label="001_01" attrib="00 00 00 00 00 00 00 00"><anim id="Nodding" target="actor" targetSpec="" />I'm so glad to see you wearing the
<tag a="125" b="5" arg="0xcd00" /> I gave
you, <tag a="110" b="3" />!
<anim id="AbsentMindedness" target="actor" targetSpec="" />That's so cool. <delay20 />I feel like an artist,
painting the world with my
fashion sense<tag a="110" b="0" /></message>
	<message label="001_02" attrib="00 00 00 00 00 00 00 00"><anim id="EmotEnd" target="actor" targetSpec="" />You are looking good in your
<tag a="125" b="5" arg="0xcd00" />, yo!<pageBreak /><anim id="Grin" target="actor" targetSpec="" />It's such a natural look for you,
like you've been rocking that
style your whole life!</message>
	<message label="001_03" attrib="00 00 00 00 00 00 00 00"><anim id="Nodding" target="actor" targetSpec="" />You have got to tell me where you
got that outfit, <tag a="110" b="3" />.<pageBreak /><anim id="Love" target="actor" targetSpec="" />I especially love your <tag a="125" b="5" arg="0xcd00" />.<delay20 /> <anim id="EmotEnd" target="actor" targetSpec="" />Wait.<pageBreak /><anim id="Shocked" target="actor" targetSpec="" />You're wearing the
<tag a="125" b="5" arg="0xcd00" /> that
I gave you, <tag a="110" b="5" />!<delay20 />
<anim id="Frantic" target="actor" targetSpec="" />How could I have parted with
something so fabulous?</message>
	<message label="002" attrib="00 00 00 00 00 00 00 00"><tag a="60" b="20" /></message>
	<message label="002_01" attrib="00 00 00 00 00 00 00 00"><anim id="Pardon" target="actor" targetSpec="" />Am I crazy, or are you wearing
the <tag a="125" b="0" arg="0x0" /> that
I gave you?
<anim id="HappyFlower" target="actor" targetSpec="" />That's so cool!<delay20 /> It's clear you
recognize good taste.</message>
	<message label="002_02" attrib="00 00 00 00 00 00 00 00"><anim id="Aha" target="actor" targetSpec="" />Ooh, I like what I see<tag a="110" b="0" />
Your <tag a="125" b="0" arg="0x0" />!<pageBreak /><anim id="WrySmile" target="actor" targetSpec="" />Don't forget who you have
to thank for that look, OK?<10_4 />
<anim id="EmotEnd" target="actor" targetSpec="" />It's <tag a="50" b="2" /><tag a="110" b="10" /> original!</message>
	<message label="002_03" attrib="00 00 00 00 00 00 00 00"><anim id="Thinking" target="actor" targetSpec="" />Hey, so you're wearing <tag a="50" b="2" />
<tag a="125" b="0" arg="0x0" />, right?<pageBreak /><anim id="QuestionMark" target="actor" targetSpec="" />Can you tell me more about that
look? <delay20 />Like, you know, what was
your inspiration for it?
<anim id="Laughing" target="actor" targetSpec="" />Ha! <delay20 />I'm kidding, I'm kidding!<delay20 />
<anim id="Grin" target="actor" targetSpec="" />I know your inspiration was me.</message>
	<message label="003" attrib="00 00 00 00 00 00 00 00"><tag a="60" b="20" /></message>
	<message label="003_01" attrib="00 00 00 00 00 00 00 00"><anim id="Aha" target="actor" targetSpec="" />Your <tag a="125" b="6" arg="0xcd01" />
says "<tag a="110" b="3" />" more than
"<tag a="110" b="3" />" itself!</message>
	<message label="003_02" attrib="00 00 00 00 00 00 00 00"><anim id="Serious" target="actor" targetSpec="" />Hold on.<delay20 /> I have a comment on
your <tag a="125" b="6" arg="0xcd01" />.<pageBreak />You. <delay frames="40" />Are.<delay frames="40" /> <anim id="Dance" target="actor" targetSpec="" />CRUSHING IT! <delay20 />Way to
make the rest of us look like fashion
fools, <tag a="110" b="3" />!</message>
	<message label="003_03" attrib="00 00 00 00 00 00 00 00"><anim id="Serious" target="actor" targetSpec="" /><tag a="50" b="3" /><tag a="110" b="3" />, your whole
ensemble today<tag a="110" b="0" /><delay20 /><anim id="EmotEnd" target="actor" targetSpec="" />it is WORKING.<pageBreak /><anim id="Nodding" target="actor" targetSpec="" />And the <tag a="125" b="6" arg="0xcd01" />
really ties it together.</message>
	<message label="004" attrib="00 00 00 00 00 00 00 00"><tag a="60" b="20" /></message>
	<message label="004_01" attrib="00 00 00 00 00 00 00 00"><anim id="Grin" target="actor" targetSpec="" />I think they should name
the <tag a="125" b="6" arg="0xcd02" /> after
you, because you are owning it!</message>
	<message label="004_02" attrib="00 00 00 00 00 00 00 00"><anim id="Serious" target="actor" targetSpec="" />That outfit is serious business, and
the <tag a="125" b="6" arg="0xcd02" />?<delay frames="40" />
<anim id="SmugFace" target="actor" targetSpec="" />Icing on the cake.
<anim id="WrySmile" target="actor" targetSpec="" />What?<delay20 /> Icing is serious business.</message>
	<message label="004_03" attrib="00 00 00 00 00 00 00 00"><anim id="Thinking" target="actor" targetSpec="" />My oh my<tag a="110" b="0" /> The look you've
come up with today<tag a="110" b="0" /><pageBreak /><anim id="EmotEnd" target="actor" targetSpec="" />It's fabulous! <delay20 />And how about the
things you can do with <tag a="50" b="2" />
<tag a="125" b="6" arg="0xcd02" /><tag a="110" b="0" /></message>
	<message label="005" attrib="00 00 00 00 00 00 00 00"><anim id="OhGeez" target="actor" targetSpec="" />Oh, <tag a="110" b="3" /><tag a="110" b="0" /> That outfit
you're wearing is perfection. <delay20 /><anim id="Eh" target="actor" targetSpec="" />And
the <tag a="125" b="6" arg="0xcd03" />?
<anim id="WrySmile" target="actor" targetSpec="" />What's more perfect than perfection?
<delay20 />Because it's that.</message>
	<message label="006" attrib="00 00 00 00 00 00 00 00"><anim id="Shocked" target="actor" targetSpec="" />Do my eyes deceive me,
or are you wearing
<tag a="50" b="2" /><tag a="125" b="6" arg="0xcd04" />?
<anim id="Nodding" target="actor" targetSpec="" />Not everyone realizes how much
impact the right footwear can make.<pageBreak /><anim id="Angry" target="actor" targetSpec="" />And don't even get me started on
what the WRONG footwear can
do for your whole look.</message>
	<message label="007" attrib="00 00 00 00 00 00 00 00"><anim id="Thinking" target="actor" targetSpec="" />That outfit you're wearing is really
unusual<tag a="110" b="0" />in a good way. <delay20 /><anim id="QuestionMark" target="actor" targetSpec="" />And you
designed it yourself, you say?
<anim id="BigSmile" target="actor" targetSpec="" />Very impressive.<delay20 /> Shocking folks
with original design is a lost art if
you ask me, <tag a="110" b="5" />.</message>
	<message label="008" attrib="00 00 00 00 00 00 00 00"><anim id="Shocked" target="actor" targetSpec="" />Whoa, are you really wearing the
signature <tag a="115" b="0" arg="0xcd02" />
<tag a="115" b="3" arg="0xcd00" />?
<anim id="QuestionMark" target="actor" targetSpec="" />Do you know <tag a="115" b="0" arg="0xcd02" />?<delay frames="40" />
<tag a="110" b="0" /><anim id="Hesitate" target="actor" targetSpec="" />Can you get me an autograph?</message>
	<message label="009" attrib="00 00 00 00 00 00 00 00"><anim id="Eh" target="actor" targetSpec="" />Whoa, that outfit you're wearing<tag a="110" b="0" />
<anim id="Thinking" target="actor" targetSpec="" />You don't see that kind of look
every day around here.
<anim id="Shocked" target="actor" targetSpec="" />Oh, it's a custom <tag a="115" b="0" arg="0xcd02" />
design? <delay20 />From <tag a="115" b="5" arg="0xcd00" />?<delay20 />
<anim id="OhGeez" target="actor" targetSpec="" />Well, no wonder!
<anim id="Smiling" target="actor" targetSpec="" />Looks like the fashion scene on
<tag a="115" b="5" arg="0xcd00" /> is really thriving!</message>
	<message label="010" attrib="00 00 00 00 00 00 00 00"><anim id="Aha" target="actor" targetSpec="" />Well, look at you! <delay frames="40" /><anim id="Nodding" target="actor" targetSpec="" />All fresh
and fancy for spring in your
<tag a="125" b="5" arg="0xcd00" />!</message>
	<message label="011" attrib="00 00 00 00 00 00 00 00"><anim id="Smiling" target="actor" targetSpec="" />Well, you're looking breezy,
<tag a="110" b="3" />!<delay20 /> <anim id="WrySmile" target="actor" targetSpec="" />Glad to see
you all decked out for the season.
<anim id="Serious" target="actor" targetSpec="" />Seriously. <delay20 />I wish I had the
good sense to be wearing
<tag a="50" b="2" /><tag a="125" b="5" arg="0xcd00" />.</message>
	<message label="012" attrib="00 00 00 00 00 00 00 00"><anim id="Aha" target="actor" targetSpec="" />Ooh, the season is turning and
you're right there with your
wardrobe.
<anim id="WrySmile" target="actor" targetSpec="" />That's to say, I really dig
the <tag a="125" b="5" arg="0xcd00" />!</message>
	<message label="013" attrib="00 00 00 00 00 00 00 00"><anim id="Cheering" target="actor" targetSpec="" />Ooh, you look toasty and trendy in
your <tag a="125" b="5" arg="0xcd00" />!</message>
	<message label="014" attrib="00 00 00 00 00 00 00 00"><anim id="Worried" target="actor" targetSpec="" />Oh, <tag a="110" b="3" /><tag a="110" b="0" />what are
you doing?<pageBreak /><anim id="WrySmile" target="actor" targetSpec="" />I've tried to pull off some bold
fashion choices in my day,
believe me.
<anim id="Negative" target="actor" targetSpec="" />But no one can pull off <tag a="50" b="2" />
<tag a="125" b="5" arg="0xcd00" /> in the
heat of the summer!</message>
	<message label="015" attrib="00 00 00 00 00 00 00 00"><anim id="Confused" target="actor" targetSpec="" />Uh<tag a="110" b="0" />are you really wearing
<tag a="50" b="2" /><tag a="125" b="5" arg="0xcd00" />?!<pageBreak /><anim id="QuestionMark" target="actor" targetSpec="" />You're not cold?<delay20 /> Like, even a little
bit?<delay20 /><anim id="ColdChill" target="actor" targetSpec="" /> I'm cold just looking at you!</message>
	<message label="016" attrib="00 00 00 00 00 00 00 00"><tag a="60" b="20" /></message>
	<message label="016_01" attrib="00 00 00 00 00 00 00 00"><anim id="Love" target="actor" targetSpec="" />Oh, <tag a="110" b="5" /><tag a="110" b="0" /> That outfit
you're wearing is straight-up
<tag a="135" b="7" arg="0xcd00" />.
<anim id="OhGeez" target="actor" targetSpec="" />And now I'm actually hungry
for <tag a="135" b="7" arg="0xcd00" /><tag a="110" b="0" /></message>
	<message label="016_02" attrib="00 00 00 00 00 00 00 00"><anim id="Silent" target="actor" targetSpec="" />Whoa.<delay20 /> It looks like you've designed
your entire outfit today around your
<tag a="125" b="5" arg="0xcd00" />, hm?<pageBreak /><anim id="Clapping" target="actor" targetSpec="" />Stunning.<delay20 /> I'm in awe of your
fashion sense, <tag a="110" b="5" />.</message>
	<message label="016_03" attrib="00 00 00 00 00 00 00 00"><anim id="Shocked" target="actor" targetSpec="" />Whoa.<delay20 /> You've done it.<delay20 /> <anim id="Clapping" target="actor" targetSpec="" />You've found
the perfect blend of cute and classy
with that outfit.<pageBreak /><anim id="QuestionMark" target="actor" targetSpec="" />And you know what ties it all
together for me, <tag a="110" b="5" />?<delay frames="40" />
<anim id="BigSmile" target="actor" targetSpec="" />Your <tag a="125" b="5" arg="0xcd00" />!</message>
	<message label="017" attrib="00 00 00 00 00 00 00 00"><tag a="60" b="20" /></message>
	<message label="017_01" attrib="00 00 00 00 00 00 00 00"><anim id="Serious" target="actor" targetSpec="" />There's something very cool about
what you're wearing today, and I
don't mean the fabric.
<anim id="AbsentMindedness" target="actor" targetSpec="" />I could see myself wearing something
similar, belting out <tag a="135" b="4" arg="0xcd00" /> in
front of a million adoring fans<tag a="110" b="0" /></message>
	<message label="017_02" attrib="00 00 00 00 00 00 00 00"><anim id="Shocked" target="actor" targetSpec="" />Yo<tag a="110" b="0" />I'm incredibly jealous of
your <tag a="125" b="5" arg="0xcd00" />!<pageBreak /><anim id="Love" target="actor" targetSpec="" />It's like you just leveled up in the
game of fashion, <tag a="110" b="5" />!</message>
	<message label="017_03" attrib="00 00 00 00 00 00 00 00"><anim id="Silent" target="actor" targetSpec="" />OK, I'm more than a little jealous
of how cool you look in your
<tag a="125" b="5" arg="0xcd00" />.<pageBreak /><anim id="Thinking" target="actor" targetSpec="" />Now the jealousy is turning into
awe<tag a="110" b="0" /><delay20 />with just a hint of rage.<delay frames="40" />
<anim id="Fuming" target="actor" targetSpec="" />ARRRRGHH!<10_4 /> <anim id="Laughing" target="actor" targetSpec="" />Just kidding. <delay20 />Ha HA!</message>
	<message label="018" attrib="00 00 00 00 00 00 00 00"><tag a="60" b="20" /></message>
	<message label="018_01" attrib="00 00 00 00 00 00 00 00"><anim id="QuestionMark" target="actor" targetSpec="" />You know what never goes out of
style? <delay frames="40" /><anim id="Nodding" target="actor" targetSpec="" />Classic stuff. <delay20 />Kinda like the
outfit you've got on right now.
<anim id="OhGeez" target="actor" targetSpec="" />Don't get me wrong.<delay20 /> I like to get
real weird with fashion, but classic
stuff is classic for a reason.</message>
	<message label="018_02" attrib="00 00 00 00 00 00 00 00"><anim id="QuestionMark" target="actor" targetSpec="" />Going back to the basics with your
<tag a="125" b="5" arg="0xcd00" />, hm?<pageBreak /><anim id="Serious" target="actor" targetSpec="" />I approve.<delay frames="40" /><anim id="Worried" target="actor" targetSpec="" /> Not that you need my
approval, but maybe I need yours?<delay20 />
Do you approve of my approval?</message>
	<message label="018_03" attrib="00 00 00 00 00 00 00 00"><anim id="Hello" target="actor" targetSpec="" />I really like your style today. <delay20 /><anim id="Nodding" target="actor" targetSpec="" />Just
simple, basic, straightforward.
<tag a="50" b="3" /><tag a="50" b="2" /><tag a="125" b="5" arg="0xcd00" />.<pageBreak /><anim id="Smiling" target="actor" targetSpec="" />It's like your clothes are taking
a backseat to let your personality
shine, <tag a="110" b="5" />!</message>
	<message label="019" attrib="00 00 00 00 00 00 00 00"><tag a="60" b="20" /></message>
	<message label="019_01" attrib="00 00 00 00 00 00 00 00"><anim id="Shocked" target="actor" targetSpec="" />Whoa! <delay20 />You are dressed to the nines
today. <delay20 /><anim id="Grin" target="actor" targetSpec="" />Maybe even the tens!<pageBreak /><anim id="QuestionMark" target="actor" targetSpec="" />What's the occasion?<delay20 /> Launching
a new fragrance?<delay20 /> Attending a new
fragrance launch?
<anim id="OhGeez" target="actor" targetSpec="" />Welp, I'm out of ideas. <delay20 />Help me
out, <tag a="110" b="3" />.</message>
	<message label="019_02" attrib="00 00 00 00 00 00 00 00"><anim id="Grin" target="actor" targetSpec="" />I don't know if you dance, but it
LOOKS like you can dance in that
outfit, <tag a="110" b="5" />.<pageBreak /><anim id="Explain" target="actor" targetSpec="" />Some folks have said I have two left
feet, but to me, that just means I can
do weirder dances. <delay20 /><anim id="Laughing" target="actor" targetSpec="" />Ha HA!</message>
	<message label="019_03" attrib="00 00 00 00 00 00 00 00"><anim id="Worried" target="actor" targetSpec="" />Ooh, I'm not sure you and I should
stand so close to each other. <delay20 />We're
like paparazzi magnets right now.<pageBreak /><anim id="Explain" target="actor" targetSpec="" />Mostly because of the super-glam
outfit you're wearing<tag a="110" b="0" />especially
<tag a="50" b="1" /><tag a="125" b="5" arg="0xcd00" />.</message>
	<message label="020" attrib="00 00 00 00 00 00 00 00"><tag a="60" b="20" /></message>
	<message label="020_01" attrib="00 00 00 00 00 00 00 00"><anim id="Love" target="actor" targetSpec="" />I'm loving your outfit today,
<tag a="110" b="5" />. <delay20 />It looks super comfy,
and also super stylish.<anim id="Nodding" target="actor" targetSpec="" />
<anim id="Eh" target="actor" targetSpec="" /><delay40 />That's like the holy grail of fashion!</message>
	<message label="020_02" attrib="00 00 00 00 00 00 00 00"><anim id="Grin" target="actor" targetSpec="" />Oh, hey! <delay20 />Working out, or hardly
working out?<delay20 /> In your fancy
<tag a="125" b="5" arg="0xcd00" />, I mean.<pageBreak /><anim id="OhGeez" target="actor" targetSpec="" />Sorry, I'm not used to sporty lingo.<delay20 />
I'm more into <tag a="135" b="8" arg="0xcd00" />, if
you hadn't noticed.</message>
	<message label="020_03" attrib="00 00 00 00 00 00 00 00"><anim id="Shocked" target="actor" targetSpec="" />Whoa, what's with the activewear
today, <tag a="110" b="5" />? <delay20 /><anim id="WrySmile" target="actor" targetSpec="" />Gonna do a
little <tag a="135" b="6" arg="0xcd00" />?<pageBreak /><anim id="OhGeez" target="actor" targetSpec="" />Oh, I just ask because of what you're
wearing. <delay20 /><anim id="Nodding" target="actor" targetSpec="" />Ready for adventure in your
<tag a="125" b="5" arg="0xcd00" />!</message>
	<message label="021" attrib="00 00 00 00 00 00 00 00"><tag a="60" b="20" /></message>
	<message label="021_01" attrib="00 00 00 00 00 00 00 00"><anim id="Smiling" target="actor" targetSpec="" />Hey, you're really dressed up today!<delay frames="40" />
<anim id="QuestionMark" target="actor" targetSpec="" />You headed to the after-party?<pageBreak /><anim id="Grin" target="actor" targetSpec="" />There's no "before" party that I
know about, but I always ask
everyone just in case. <delay20 /><anim id="Laughing" target="actor" targetSpec="" />Ha HA!</message>
	<message label="021_02" attrib="00 00 00 00 00 00 00 00"><anim id="AbsentMindedness" target="actor" targetSpec="" />Hmm, there's something about your
outfit today that just screams posh.<pageBreak /><anim id="WrySmile" target="actor" targetSpec="" />I mean, it SINGS posh in a perfect
falsetto, hitting every note true.<delay20 />
<anim id="Laughing" target="actor" targetSpec="" />Ha HA!</message>
	<message label="021_03" attrib="00 00 00 00 00 00 00 00"><anim id="Smiling" target="actor" targetSpec="" /><tag a="50" b="3" /><tag a="110" b="5" />, you're looking slick
today. <delay20 /><anim id="Thinking" target="actor" targetSpec="" />I'd call that look<tag a="110" b="0" />understated
but totally over the top!<pageBreak /><anim id="AbsentMindedness" target="actor" targetSpec="" />It's like<tag a="110" b="0" />you could wear that to the
opera, but then tuck into a messy
<tag a="135" b="3" arg="0xcd00" /> appetizer after. <delay20 /><anim id="Laughing" target="actor" targetSpec="" />Ha!</message>
	<message label="101" attrib="00 00 00 00 00 00 00 00"><tag a="60" b="20" /></message>
	<message label="101_01" attrib="00 00 00 00 00 00 00 00"><anim id="WrySmile" target="actor" targetSpec="" />Heh.<delay20 /> You sure seem to wear that
outfit a lot.<pageBreak /><anim id="Frantic" target="actor" targetSpec="" />OH! <delay20 />I didn't mean it that way.<delay20 /> It
looks great on you, so why wouldn't
you wear it all the time?
<anim id="EmotEnd" target="actor" targetSpec="" />Whew. <delay20 />Saved it.</message>
	<message label="101_02" attrib="00 00 00 00 00 00 00 00"><anim id="Thinking" target="actor" targetSpec="" />That outfit is getting to be, like,
your signature outfit.<delay20 /> <anim id="Aha" target="actor" targetSpec="" />That's good
for your brand, <tag a="110" b="3" />!</message>
	<message label="101_03" attrib="00 00 00 00 00 00 00 00"><anim id="Nodding" target="actor" targetSpec="" />There's something special about the
combination of <tag a="110" b="3" />
and <tag a="125" b="5" arg="0xcd00" />.</message>
	<message label="101_04" attrib="00 00 00 00 00 00 00 00"><anim id="Hello" target="actor" targetSpec="" />I see you're still rocking your
<tag a="125" b="5" arg="0xcd00" /> today<tag a="110" b="0" /><pageBreak /><anim id="Shocked" target="actor" targetSpec="" />Did you get cast in something?<delay20 />
Are you method acting right now?<pageBreak /><anim id="Frantic" target="actor" targetSpec="" />OK, OK, don't break character,
but raise your left eyebrow slightly
if the answer is yes!</message>
	<message label="101_05" attrib="00 00 00 00 00 00 00 00"><anim id="Grin" target="actor" targetSpec="" />What can I say?<delay20 /> You look sharp in
your <tag a="125" b="5" arg="0xcd00" /> as usual, <tag a="110" b="3" />!</message>
	<message label="201" attrib="00 00 00 00 00 00 00 00"><tag a="60" b="7" arg="0xfb00 0xfc00 0xcd00" /></message>
	<message label="251" attrib="00 00 00 00 00 00 00 00"><anim id="Smiling" target="actor" targetSpec="" />I'm loving this feline-themed
ensemble you've got going on today.<pageBreak /><anim id="Aha" target="actor" targetSpec="" />Ooh! <delay40 /><anim id="BigSmile" target="actor" targetSpec="" />I hope this is the start of a hot
new trend. <delay20 />'Cause then I can say<delay8 /><anim id="SmugFace" target="actor" targetSpec="" /> I
had this look before it was cool.</message>
	<message label="252" attrib="00 00 00 00 00 00 00 00"><anim id="Thinking" target="actor" targetSpec="" />There's something enigmatic, <delay8 />yet
completely adorable about your vibe
today, <tag a="110" b="3" />.
<anim id="Smiling" target="actor" targetSpec="" />Yeah. <delay20 />Whatever you're doing,<delay8 /> keep
doing it, <tag a="110" b="5" />.</message>
	<message label="202" attrib="00 00 00 00 00 00 00 00"><anim id="Eh" target="actor" targetSpec="" />Woah! <delay20 />You are, like, Bunny Day
incarnate.<delay20 /> And may I just say, <delay8 /><anim id="BigSmile" target="actor" targetSpec="" />you've
achieved eggs-traordinary results.
<anim id="FaintSmile" target="actor" targetSpec="" />That's what I like about you. <delay20 />When it
comes to fashion, you never hold
back, <tag a="110" b="5" />.</message>
	<message label="203" attrib="00 00 00 00 00 00 00 00"><anim id="Thinking" target="actor" targetSpec="" />So I noticed that you're wearing
<tag a="50" b="2" /><tag a="125" b="0" arg="0x0" />.<pageBreak /><anim id="Hesitate" target="actor" targetSpec="" />Is something special going on today?<delay8 />
Because I don't usually see you this
dressed up, <tag a="110" b="3" /><tag a="110" b="0" />
<anim id="QuestionMark" target="actor" targetSpec="" />You going to a party? <delay8 />Is it a secret
party?<delay20 /> When does it start?<anim id="Serious" target="actor" targetSpec="" /> You know
what?<delay8 /> It doesn't matter.
If you need a DJ,<anim id="EmotEnd" target="actor" targetSpec="" /> I'm free.</message>
	<message label="204" attrib="00 00 00 00 00 00 00 00"><anim id="FaintSmile" target="actor" targetSpec="" />Sweet outfit, <tag a="110" b="5" />.<pageBreak /><anim id="Explain" target="actor" targetSpec="" />It can be hard to walk that fine line
between nutrish and delish,<delay20 /><anim id="Clapping" target="actor" targetSpec="" /> but you
nailed it, <tag a="110" b="3" />.</message>
	<message label="205" attrib="00 00 00 00 00 00 00 00"><tag a="60" b="7" arg="0xfd10 0xfe00 0xcd00" /></message>
	<message label="253" attrib="00 00 00 00 00 00 00 00"><anim id="Shocked" target="actor" targetSpec="" />Whoa! <delay frames="40" />I got jealous that there was
another frog here for a second there.<delay20 />
<anim id="Laughing" target="actor" targetSpec="" />But it's just you, <tag a="110" b="3" />!<pageBreak /><anim id="Serious" target="actor" targetSpec="" />I'm honored that you're cosplaying
as me at <tag a="110" b="10" />-Con this
year, <tag a="110" b="5" />.</message>
	<message label="254" attrib="00 00 00 00 00 00 00 00"><anim id="Smiling" target="actor" targetSpec="" />Well, aren't you looking froggy
today, <tag a="110" b="3" />?<pageBreak /><anim id="EmotEnd" target="actor" targetSpec="" />You look like you're ready to hop
right down a runway, <tag a="110" b="5" />!</message>
	<message label="206" attrib="00 00 00 00 00 00 00 00"><anim id="Serious" target="actor" targetSpec="" />That outfit you're wearing is sending
a VERY strong message right now.<pageBreak /><anim id="WrySmile" target="actor" targetSpec="" />It says, "I'm a person who knows
starboard from port and isn't afraid
of a little adventure."</message>
	<message label="207" attrib="00 00 00 00 00 00 00 00"><anim id="Thinking" target="actor" targetSpec="" />Your outfit has me thinking<tag a="110" b="0" /><pageBreak /><anim id="QuestionMark" target="actor" targetSpec="" />Do you think that mermaids are real?<delay frames="40" />
<anim id="AbsentMindedness" target="actor" targetSpec="" />And if so, do you think they LIKE to
swim, or are they just bored by it?</message>
	<message label="208" attrib="00 00 00 00 00 00 00 00"><anim id="Thinking" target="actor" targetSpec="" />You know, I never thought about it
before, but those can be stylish.<delay20 /> Your
<tag a="125" b="0" arg="0x0" />, I mean.<pageBreak /><anim id="Negative" target="actor" targetSpec="" />I'm not saying I'd wear one to an
important audition, but<tag a="110" b="0" /><delay20 /><anim id="IdeaBulb" target="actor" targetSpec="" />maybe for
a movie about giant sharks<tag a="110" b="0" /></message>
	<message label="209" attrib="00 00 00 00 00 00 00 00"><anim id="TakenAback" target="actor" targetSpec="" />Did you just come from a movie
set or what, <tag a="110" b="5" />?<pageBreak /><anim id="Thinking" target="actor" targetSpec="" />Wait<tag a="110" b="0" />don't tell me<tag a="110" b="0" /><delay20 /><anim id="Crying" target="actor" targetSpec="" /> You got the
part in that <tag a="135" b="4" arg="0xcd00" /> opera and
I didn't! <delay20 />Ooh, I gotta fire my agent<tag a="110" b="0" /></message>
	<message label="210" attrib="00 00 00 00 00 00 00 00"><anim id="BigSmile" target="actor" targetSpec="" />You are looking SHARP today, my
friend! <delay20 />Dare I say<tag a="110" b="0" /><tag a="110" b="5" />?<pageBreak /><anim id="Worried" target="actor" targetSpec="" />Wait<tag a="110" b="0" />are you headed to a party
that I wasn't invited to? <delay20 /><anim id="Frantic" target="actor" targetSpec="" />Or even
worse<tag a="110" b="0" />an AFTERparty?</message>
	<message label="211" attrib="00 00 00 00 00 00 00 00"><anim id="Love" target="actor" targetSpec="" />Wow, you look downright elegant
today, <tag a="110" b="3" />!<pageBreak /><anim id="Grin" target="actor" targetSpec="" />I'd say you're ready for anything,
from a formal dinner party with
royalty to <tag a="135" b="8" arg="0xcd00" />.</message>
	<message label="212" attrib="00 00 00 00 00 00 00 00"><tag a="60" b="7" arg="0xff06 0x0 0xcd01" /></message>
	<message label="255" attrib="00 00 00 00 00 00 00 00"><anim id="Shocked" target="actor" targetSpec="" />Whoa, look at us! <delay20 /><anim id="Negative" target="actor" targetSpec="" />Normally I'd say
it's a bad idea to show up at the club
looking like twins.<pageBreak /><anim id="WrySmile" target="actor" targetSpec="" />But with you? <delay20 />Here? <delay20 />We're starting a
trend, right now!<delay20 /><anim id="BigSmile" target="actor" targetSpec="" /> <tag a="50" b="3" /><tag a="110" b="8" />
Rabbit Club, <tag a="110" b="5" />!</message>
	<message label="256" attrib="00 00 00 00 00 00 00 00"><anim id="Smiling" target="actor" targetSpec="" />You're looking hippity and full of hop
today, <tag a="110" b="5" />. <delay frames="40" /><anim id="Love" target="actor" targetSpec="" />LOVE the ears
and tail!</message>
	<message label="213" attrib="00 00 00 00 00 00 00 00"><tag a="60" b="32" arg="0x2e 0x62 0x65 0x61 0x3e 0x32 0x35 0x37 0x2c 0x63 0x62 0x72 0x3e 0x32 0x35 0x37 0x2c 0x65 0x74 0x63 0x3e 0x32 0x35 0x38" /></message>
	<message label="257" attrib="00 00 00 00 00 00 00 00"><anim id="Thinking" target="actor" targetSpec="" />Wait, uh<tag a="110" b="0" /><delay frames="40" /> <anim id="Shocked" target="actor" targetSpec="" />Are we related?<delay20 /> Were you
at the family reunion last summer?<pageBreak /><anim id="Worried" target="actor" targetSpec="" />You remember?<delay20 /> The one where I put
on that experimental one-bear show
about <tag a="135" b="8" arg="0xcd00" />?<pageBreak /><anim id="Sighing" target="actor" targetSpec="" />Oh, it's just an outfit.<delay20 /> Probably for
the best. <delay20 /><anim id="Laughing" target="actor" targetSpec="" />Forget I said anything.</message>
	<message label="258" attrib="00 00 00 00 00 00 00 00"><anim id="Grin" target="actor" targetSpec="" />Going for a fuzzy and ferocious
look today, eh?<delay20 /><anim id="Cheering" target="actor" targetSpec="" /> I like it!<pageBreak /><anim id="WrySmile" target="actor" targetSpec="" />Don't maul me for saying it, but
I can barely stand how sharp you
look, <tag a="110" b="5" />!</message>
	<message label="214" attrib="00 00 00 00 00 00 00 00"><tag a="60" b="7" arg="0x302 0x401 0xcd01" /></message>
	<message label="259" attrib="00 00 00 00 00 00 00 00"><anim id="Shocked" target="actor" targetSpec="" />Your hair looks incredible today!<delay frames="40" />
<anim id="Love" target="actor" targetSpec="" />The body! <10_4 /><anim id="EmotEnd" target="actor" targetSpec="" />The bounce!<10_4 /> <anim id="BigSmile" target="actor" targetSpec="" />The style!<delay8 />
It's too much!<pageBreak /><anim id="Blushing" target="actor" targetSpec="" />Can you give me a shampoo
recommendation? <delay20 />I want to look
even MORE like you, <tag a="110" b="5" />!</message>
	<message label="260" attrib="00 00 00 00 00 00 00 00"><anim id="Love" target="actor" targetSpec="" />LOVE the outfit, <tag a="110" b="3" />.<pageBreak /><anim id="Explain" target="actor" targetSpec="" />I hear that faux wool is soft, shrink-
proof, and completely fabulous.<delay frames="40" />
<anim id="Shocked" target="actor" targetSpec="" />How does it do all that?!</message>
	<message label="215" attrib="00 00 00 00 00 00 00 00"><anim id="Eh" target="actor" targetSpec="" />I'm getting a real homemade vibe
from your outfit today, <tag a="110" b="5" />.<pageBreak /><anim id="QuestionMark" target="actor" targetSpec="" />Did you get it from your mom?<10_4 />
<anim id="EmotEnd" target="actor" targetSpec="" />Well, maybe she should be a fashion
designer<tag a="110" b="0" />if she isn't already!</message>
	<message label="216" attrib="00 00 00 00 00 00 00 00"><anim id="Eh" target="actor" targetSpec="" />Wow, is that official DAL gear you're
wearing, <tag a="110" b="5" />?<pageBreak /><anim id="BigSmile" target="actor" targetSpec="" />They're known for great service and
customer satisfaction, but now they
make high-quality activewear too?<pageBreak /><anim id="EmotEnd" target="actor" targetSpec="" /><tag a="110" b="0" /><anim id="Scheming" target="actor" targetSpec="" />Just go with it. <delay20 />I'm trying to
become a DAL influencer<tag a="110" b="0" /></message>
	<message label="217" attrib="00 00 00 00 00 00 00 00"><anim id="Eh" target="actor" targetSpec="" />You look like you're ready for a
costume party<tag a="110" b="0" /><delay20 /><anim id="QuestionMark" target="actor" targetSpec="" />but are you
TRULY ready, <tag a="110" b="3" />?<pageBreak /><anim id="QuestionMark" target="actor" targetSpec="" />Have you studied your character bio?<delay8 />
Practiced your accent? <delay8 />Taken the
swordplay and combat classes?<pageBreak /><anim id="Shocked" target="actor" targetSpec="" />What do you mean, "It's not a
movie"?<delay frames="40" /> <anim id="EmotEnd" target="actor" targetSpec="" />Life's a movie when you
live like me, <tag a="110" b="5" />!</message>
	<message label="218" attrib="00 00 00 00 00 00 00 00"><anim id="Serious" target="actor" targetSpec="" />Whoa! <delay20 />If you're dressed like that,
you better have a gift for me,
<tag a="110" b="5" />.<10_4 /> <anim id="Laughing" target="actor" targetSpec="" />Ha HA! <delay20 />Just kidding.<pageBreak /><anim id="Hesitate" target="actor" targetSpec="" />But, uh<tag a="110" b="0" />if you DO have a gift,
I wouldn't say no<tag a="110" b="0" /></message>
	<message label="301" attrib="00 00 00 00 00 00 00 00"><anim id="Eh" target="actor" targetSpec="" />How'd you know I was casting for my
latest film project,<delay8 /><anim id="SmugFace" target="actor" targetSpec="" /> "Knights of the
Gilded <capitaliseNextWord /><tag a="135" b="5" arg="0xcd00" />"?
<anim id="Serious" target="actor" targetSpec="" />I don't know how you found out
about it,<delay8 /> but I'll mail you a copy of
the NDA, and we'll go from there.</message>
	<message label="302" attrib="00 00 00 00 00 00 00 00"><anim id="Nodding" target="actor" targetSpec="" />It makes total sense that you want to
be a pilot, <tag a="110" b="3" />.<pageBreak />The outfit alone commands respect.<delay20 />
<anim id="Serious" target="actor" targetSpec="" />I'd buckle my seatbelt right now if
you told me to,<delay8 /> without question.
<anim id="Smiling" target="actor" targetSpec="" />You know, if I had one on me.</message>
	<message label="303" attrib="00 00 00 00 00 00 00 00"><anim id="FaintSmile" target="actor" targetSpec="" />I can tell from your outfit that you
have some experience on the ice.<pageBreak /><anim id="Serious" target="actor" targetSpec="" />As a longtime fan of ice-skating slash
dancing,<delay8 /> I've always wanted to
know<tag a="110" b="0" /> <anim id="Shaking" target="actor" targetSpec="" />Aren't you freezing?!</message>
	<message label="304" attrib="00 00 00 00 00 00 00 00"><anim id="Hello" target="actor" targetSpec="" />Ah, I didn't know you were the
sporting type!<pageBreak /><anim id="WrySmile" target="actor" targetSpec="" />You ready for a little footy? <delay8 />A little
kicksy jumpsy? <delay8 />A bit of the old
pass-shoot-dance routine?
<anim id="OhGeez" target="actor" targetSpec="" />Ah, you got me. <delay20 />I have no idea
what I'm talking about. <delay20 /><anim id="QuestionMark" target="actor" targetSpec="" />Was it
<tag a="135" b="6" arg="0xcd00" />?</message>
	<message label="305" attrib="00 00 00 00 00 00 00 00"><anim id="QuestionMark" target="actor" targetSpec="" />Say, can you tell me where I can find
the best <tag a="135" b="3" arg="0xcd00" /> there is to
be found on <tag a="110" b="8" />?<pageBreak /><anim id="Laughing" target="actor" targetSpec="" /><tag a="50" b="3" /><tag a="110" b="5" />, I'm just messing with
you because of your outfit! <delay frames="40" /><anim id="Serious" target="actor" targetSpec="" />But if
you have a recommendation<tag a="110" b="0" /></message>
	<message label="306" attrib="00 00 00 00 00 00 00 00"><anim id="WrySmile" target="actor" targetSpec="" />What's with the disguise?<delay20 /> What kind
of sneaky plans do you have up your
sleeve, <tag a="110" b="5" />?<pageBreak /><anim id="Serious" target="actor" targetSpec="" />Whatever it is, count me<tag a="110" b="0" /><delay20 /><anim id="EmotEnd" target="actor" targetSpec="" />IN!</message>
	<message label="307" attrib="00 00 00 00 00 00 00 00"><anim id="AbsentMindedness" target="actor" targetSpec="" />Oh, that outfit you're wearing takes
me back, <tag a="110" b="3" /><tag a="110" b="0" /><pageBreak /><anim id="Nodding" target="actor" targetSpec="" />I remember being the most popular
<tag a="110" b="15" /> in school, captain of the
<tag a="135" b="6" arg="0xcd00" /> team<tag a="110" b="0" /><pageBreak /><anim id="Sighing" target="actor" targetSpec="" />Ah, but then I threw it all away when
the government needed me to go
undercover and break up a spy ring.<pageBreak /><anim id="Blushing" target="actor" targetSpec="" />Uh<tag a="110" b="0" />some portions of that may have
been inspired by fictional events.</message>
	<message label="308" attrib="00 00 00 00 00 00 00 00"><anim id="Aha" target="actor" targetSpec="" />Ooh, going for a ride?<delay20 /> That sounds
fun, <tag a="110" b="5" />.<pageBreak /><anim id="OhGeez" target="actor" targetSpec="" />I'd go with you, but my hairstyle
isn't rated for anything above
five miles an hour.</message>
	<message label="309" attrib="00 00 00 00 00 00 00 00"><anim id="Shocked" target="actor" targetSpec="" />Whoa. <delay frames="40" />Not everyone can pull off
such a flashy outfit.<delay frames="40" /> <anim id="BigSmile" target="actor" targetSpec="" />But you are
NOODLING right now, <tag a="110" b="5" />!<pageBreak /><anim id="Blushing" target="actor" targetSpec="" />Do you like that?<delay8 /> Noodling?<delay20 /> I'm
trying to make it catch on.</message>
	<message label="401" attrib="00 00 00 00 00 00 00 00"><tag a="60" b="20" /></message>
	<message label="401_01" attrib="00 00 00 00 00 00 00 00"><anim id="Thinking" target="actor" targetSpec="" />Haven't I seen you in that outfit
before? <delay40 /><anim id="EmotEnd" target="actor" targetSpec="" />Wait. <delay20 /><anim id="Shocked" target="actor" targetSpec="" />Is wearing the same
thing over and over again hip now?
<anim id="Cheering" target="actor" targetSpec="" />Finally! <delay20 /><anim id="Clapping" target="actor" targetSpec="" />I've been trying to make this
happen for years, <tag a="110" b="5" />!</message>
	<message label="401_02" attrib="00 00 00 00 00 00 00 00"><anim id="Hello" target="actor" targetSpec="" />This is your favorite outfit, isn't it?<delay20 />
<anim id="SmugFace" target="actor" targetSpec="" />I knew it. <delay8 />I have a nose for this kind
of thing, <tag a="110" b="5" />.
<anim id="Grin" target="actor" targetSpec="" />Just call me <tag a="110" b="10" /><tag a="110" b="0" /><delay20 />
fashion detective!<delay20 /><anim id="Laughing" target="actor" targetSpec="" /> Ha HA!</message>
	<message label="401_03" attrib="00 00 00 00 00 00 00 00"><anim id="Nodding" target="actor" targetSpec="" />I've always loved that outfit on you.<delay20 />
<anim id="SmugFace" target="actor" targetSpec="" />I consider it to be the centerpiece of
the <tag a="110" b="3" /> aesthetic.</message>
	<message label="501" attrib="00 00 00 00 00 00 00 00"><tag a="60" b="20" /></message>
	<message label="501_01" attrib="00 00 00 00 00 00 00 00"><anim id="Shocked" target="actor" targetSpec="" />Whoa, look who's showing off!<delay frames="40" />
<anim id="Nodding" target="actor" targetSpec="" />I'm really loving the bold look
you're going for, <tag a="110" b="3" />.</message>
	<message label="501_02" attrib="00 00 00 00 00 00 00 00"><anim id="Thinking" target="actor" targetSpec="" />There's something different about
you today<tag a="110" b="0" /><delay frames="40" /> <anim id="QuestionMark" target="actor" targetSpec="" />Did you get a haircut
or something?
<anim id="Laughing" target="actor" targetSpec="" />Ha HA! <delay20 />I'm just teasing.<delay20 /> I love that
you're making such a bold statement.<delay20 />
<anim id="WrySmile" target="actor" targetSpec="" />And the statement is "<tag a="110" b="5" />"!</message>
	<message label="501_03" attrib="00 00 00 00 00 00 00 00"><anim id="Pardon" target="actor" targetSpec="" /><tag a="110" b="0" />Uh<tag a="110" b="0" /><delay frames="40" /><pageBreak /><anim id="Shocked" target="actor" targetSpec="" />Oh! <delay20 />Sorry, I was staring, wasn't I?<delay20 />
<anim id="Explain" target="actor" targetSpec="" />It's just that you look so different
like that!<pageBreak /><anim id="Worried" target="actor" targetSpec="" />Good different, not bad different,
I mean. <delay frames="40" /><anim id="Sighing" target="actor" targetSpec="" /><colour id="4" />Whew. Saved it.<colour id="65535" /></message>
</msbt>